<?xml version="1.0" encoding="utf-8" ?>
<dwsync>
<file name="admin-language-switcher.php" server="ftp.al-zahira.org" local="130801728048424687" remote="130801627800000000" Dst="2" />
<file name="compatibility-packages.php" server="ftp.al-zahira.org" local="130801728044274449" remote="130801627800000000" Dst="2" />
<file name="dashboard-widget.php" server="ftp.al-zahira.org" local="130801728011522576" remote="130801627800000000" Dst="2" />
<file name="debug-information.php" server="ftp.al-zahira.org" local="130801728009282448" remote="130801627800000000" Dst="2" />
<file name="language-selector-mobile.php" server="ftp.al-zahira.org" local="130801728017402913" remote="130801627800000000" Dst="2" />
<file name="edit-languages.php" server="ftp.al-zahira.org" local="130801727974550461" remote="130801627800000000" Dst="2" />
<file name="language-selector.php" server="ftp.al-zahira.org" local="130801727991901454" remote="130801627800000000" Dst="2" />
<file name="menu-footer.php" server="ftp.al-zahira.org" local="130801727980570806" remote="130801627800000000" Dst="2" />
<file name="languages.php" server="ftp.al-zahira.org" local="130801728030203645" remote="130801627800000000" Dst="2" />
<file name="network.php" server="ftp.al-zahira.org" local="130801728021313136" remote="130801627800000000" Dst="2" />
<file name="post-menu.php" server="ftp.al-zahira.org" local="130801727953459255" remote="130801627800000000" Dst="2" />
<file name="support.php" server="ftp.al-zahira.org" local="130801727997721787" remote="130801627800000000" Dst="2" />
<file name="taxonomy-translation.php" server="ftp.al-zahira.org" local="130801727980290790" remote="130801627800000000" Dst="2" />
<file name="theme-plugins-compatibility.php" server="ftp.al-zahira.org" local="130801728042524349" remote="130801627800000000" Dst="2" />
<file name="theme-localization.php" server="ftp.al-zahira.org" local="130801727947398909" remote="130801627800000000" Dst="2" />
<file name="translation-options.php" server="ftp.al-zahira.org" local="130801727986101122" remote="130801627800000000" Dst="2" />
<file name="wpml-admin-lang-switcher.class.php" server="ftp.al-zahira.org" local="130801727950049060" remote="130801627800000000" Dst="2" />
<file name="troubleshooting.php" server="ftp.al-zahira.org" local="130801727974140438" remote="130801627800000000" Dst="2" />
<file name="upgrade_notice.php" server="ftp.al-zahira.org" local="130801727962649781" remote="130801627800000000" Dst="2" />
<file name="wpml-admin-scripts-setup.class.php" server="ftp.al-zahira.org" local="130801728015312793" remote="130801627800000000" Dst="2" />
<file name="wpml-language-filter-bar.class.php" server="ftp.al-zahira.org" local="130801727986981172" remote="130801627800000000" Dst="2" />
<file name="wpml-post-edit-screen.class.php" server="ftp.al-zahira.org" local="130801727956329419" remote="130801627800000000" Dst="2" />
<file name="wpml-post-status-display.class.php" server="ftp.al-zahira.org" local="130801727992781504" remote="130801627800000000" Dst="2" />
<file name="wpml-translation-selector.class.php" server="ftp.al-zahira.org" local="130801728036013977" remote="130801627800000000" Dst="2" />
<file name="wpml-troubleshooting-terms-menu.class.php" server="ftp.al-zahira.org" local="130801728028993575" remote="130801627800000000" Dst="2" />
<file name="_custom_types_translation.php" server="ftp.al-zahira.org" local="130801727968580120" remote="130801627800000000" Dst="2" />
<file name="_posts_sync_options.php" server="ftp.al-zahira.org" local="130801728023253247" remote="130801627800000000" Dst="2" />
</dwsync>